<?xml version='1.0'?>

<coherence xmlns:xsi="http://www.w3.org/2001/XMLSchema-instance"
           xmlns="http://xmlns.oracle.com/coherence/coherence-operational-config"
           xsi:schemaLocation="http://xmlns.oracle.com/coherence/coherence-operational-config coherence-operational-config.xsd"
    >
    <cluster-config>

        <unicast-listener>
            <port system-property="tangosol.coherence.localport">20000</port>
        </unicast-listener>

        <multicast-listener>
            <time-to-live system-property="tangosol.coherence.ttl">4</time-to-live>
            <join-timeout-milliseconds system-property="tangosol.coherence.join.timeout">3000</join-timeout-milliseconds>
        </multicast-listener>

        <shutdown-listener>
            <enabled system-property="tangosol.coherence.shutdownhook">graceful</enabled>
        </shutdown-listener>

        <service-guardian>
            <service-failure-policy system-property="tangosol.coherence.service.failure.policy">logging</service-failure-policy>
        </service-guardian>

        <packet-publisher>
            <packet-delivery>
                <timeout-milliseconds system-property="tangosol.coherence.packet.timeout.milliseconds">60000</timeout-milliseconds>
            </packet-delivery>
        </packet-publisher>

    </cluster-config>

    <configurable-cache-factory-config>
        <init-params>
            <init-param>
                <param-type>java.lang.String</param-type>
                <param-value system-property="tangosol.coherence.cacheconfig">test-cache-config.xml</param-value>
            </init-param>
        </init-params>
    </configurable-cache-factory-config>
</coherence>
